pyspark_project_setup.py
automate_pyspark_project_setup-1.0.0.dist-info/METADATA
automate_pyspark_project_setup-1.0.0.dist-info/WHEEL
automate_pyspark_project_setup-1.0.0.dist-info/entry_points.txt
automate_pyspark_project_setup-1.0.0.dist-info/top_level.txt
automate_pyspark_project_setup-1.0.0.dist-info/RECORD
