Metadata-Version: 2.1
Name: automate-pyspark-project-setup
Version: 1.0.0
Summary: Program to automate folder creation
Home-page: UNKNOWN
Author: Sagar Lakshmipathy
Author-email: 18vidhyasagar@email.com
License: UNKNOWN
Platform: UNKNOWN
Requires-Dist: requests
Requires-Dist: click
